LICENSE
README.md
gamesortvisualize/__init__.py
gamesortvisualize/main.py
gamesortvisualize-0.1.1.dist-info/LICENSE
gamesortvisualize-0.1.1.dist-info/WHEEL
gamesortvisualize-0.1.1.dist-info/METADATA
gamesortvisualize-0.1.1.dist-info/RECORD
