Metadata-Version: 2.1
Name: gamesortvisualize
Version: 0.1.1
Summary: A Sorting Visualizer for Sorting Algorithms
Home-page: https://github.com/sakthiRathinam/gamesortvisualize
License: MIT-LICENSE
Keywords: sortingvisualizer,pygamesorting
Author: sakthiRatnam
Author-email: sakthiratnam050@gmail.com
Requires-Python: >=3.6,<4.0
Classifier: License :: Other/Proprietary License
Classifier: Programming Language :: Python :: 3
Classifier: Programming Language :: Python :: 3.10
Classifier: Programming Language :: Python :: 3.6
Classifier: Programming Language :: Python :: 3.7
Classifier: Programming Language :: Python :: 3.8
Classifier: Programming Language :: Python :: 3.9
Requires-Dist: pygame (>=2.1.0,<3.0.0)
Project-URL: Documentation, https://github.com/sakthiRathinam/gamesortvisualize
Project-URL: Repository, https://github.com/sakthiRathinam/gamesortvisualize
